asynciodize/__init__.py
asynciodize/asynciodize.py
asynciodize-0.1b2.dist-info/LICENSE.txt
asynciodize-0.1b2.dist-info/METADATA
asynciodize-0.1b2.dist-info/WHEEL
asynciodize-0.1b2.dist-info/top_level.txt
asynciodize-0.1b2.dist-info/RECORD
