Metadata-Version: 2.1
Name: asynciodize
Version: 0.1b2
Summary: A package to wrap/decorate blocking functions for use in asyncIO
Home-page: https://github.com/pibone/asynciodize
Download-URL: https://github.com/pibone/asynciodize/archive/refs/tags/v0.1-beta.2.tar.gz
Author: Daniel Peña Iglesias
Author-email: danpeis@gmail.com
License: MIT
Keywords: asyncio,blocking,multithreading
Classifier: Development Status :: 4 - Beta
Classifier: Intended Audience :: Developers
Classifier: Topic :: Software Development :: Libraries
Classifier: License :: OSI Approved :: MIT License
Classifier: Programming Language :: Python :: 3
Classifier: Programming Language :: Python :: 3.9
License-File: LICENSE.txt
Requires-Dist: asyncio
